is3_python_sync_plugin/__init__.py
is3_python_sync_plugin/controller/__init__.py
is3_python_sync_plugin/controller/plugin_controller.py
is3_python_sync_plugin/domain/__init__.py
is3_python_sync_plugin/domain/data_task_type.py
is3_python_sync_plugin/domain/task_node_and_data.py
is3_python_sync_plugin/domain/task_node_result.py
is3_python_sync_plugin/interface/__init__.py
is3_python_sync_plugin/interface/task_node_processor.py
is3_python_sync_plugin/nacos_server/__init__.py
is3_python_sync_plugin/nacos_server/nacos_server.py
is3_python_sync_plugin/utils/__init__.py
is3_python_sync_plugin/utils/config_util.py
is3_python_sync_plugin/utils/is3_request_util.py
is3_python_sync_plugin/utils/load_config.py
is3_python_sync_plugin/utils/logger.py
is3_python_sync_plugin/utils/plugin_log_util.py
is3_python_sync_plugin-1.0.dist-info/LICENSE
is3_python_sync_plugin-1.0.dist-info/METADATA
is3_python_sync_plugin-1.0.dist-info/WHEEL
is3_python_sync_plugin-1.0.dist-info/entry_points.txt
is3_python_sync_plugin-1.0.dist-info/top_level.txt
is3_python_sync_plugin-1.0.dist-info/RECORD
