Metadata-Version: 2.1
Name: is3_python_sync_plugin
Version: 1.0
Summary: is3 python sync plugin
Author: chaser
Author-email: sxing.liu@foxmail.com
Classifier: Programming Language :: Python :: 3
Classifier: License :: OSI Approved :: MIT License
Classifier: Operating System :: OS Independent
License-File: LICENSE
Requires-Dist: flask ==3.0.3
Requires-Dist: flasgger ==0.9.7.1
Requires-Dist: gunicorn
Requires-Dist: requests ==2.32.3
Requires-Dist: nacos-sdk-python-is3
Requires-Dist: setuptools ==65.5.0
